{
  "name": "Pass-the-Hash-Guidance",
  "repositoryURL": "https://github.com/nsacyber/Pass-the-Hash-Guidance",
  "description": "Configuration guidance for implementing Pass-the-Hash mitigations. #nsacyber",
  "permissions": {
    "licenses": [
      {
        "URL": "https://github.com/nsacyber/Pass-the-Hash-Guidance/blob/master/LICENSE.md",
        "name": "CC0-1.0"
      }
    ],
    "usageType": "openSource"
  },
  "laborHours": 1,
  "tags": [
    "pass-the-hash",
    "pth",
    "windows"
  ],
  "contact": {
    "email": "iad_ccc@nsa.gov",
    "URL": "https://www.iad.gov/iad/library/supporting-documents/faq/iad-contact-list.cfm",
    "name": "NSA Client Contact Center",
    "phone": "410-854-4200"
  },
  "status": "Archival",
  "vcs": "git",
  "homepageURL": "https://github.com/nsacyber/Pass-the-Hash-Guidance",
  "downloadURL": "https://github.com/nsacyber/Pass-the-Hash-Guidance/archive/master.zip",
  "disclaimerURL": "https://github.com/nsacyber/Pass-the-Hash-Guidance/blob/master/DISCLAIMER.md",
  "date": {
    "created": "2014-12-29",
    "metadataLastUpdated": "2018-08-31",
    "lastModified": "2016-11-25"
  },
  "languages": [
    "PowerShell"
  ]
}
